tap_zendesk/__init__.py
tap_zendesk/discover.py
tap_zendesk/metrics.py
tap_zendesk/streams.py
tap_zendesk/sync.py
tap_zendesk/schemas/agents_activity.json
tap_zendesk/schemas/articles.json
tap_zendesk/schemas/call_legs.json
tap_zendesk/schemas/calls.json
tap_zendesk/schemas/group_memberships.json
tap_zendesk/schemas/groups.json
tap_zendesk/schemas/macros.json
tap_zendesk/schemas/organization_memberships.json
tap_zendesk/schemas/organizations.json
tap_zendesk/schemas/satisfaction_ratings.json
tap_zendesk/schemas/sla_policies.json
tap_zendesk/schemas/tags.json
tap_zendesk/schemas/ticket_audits.json
tap_zendesk/schemas/ticket_comments.json
tap_zendesk/schemas/ticket_fields.json
tap_zendesk/schemas/ticket_forms.json
tap_zendesk/schemas/ticket_metric_events.json
tap_zendesk/schemas/ticket_metrics.json
tap_zendesk/schemas/tickets.json
tap_zendesk/schemas/users.json
tap_zendesk/schemas/shared/attachments.json
tap_zendesk/schemas/shared/metadata.json
tap_zendesk/schemas/shared/via.json
tap_zendesk/schemas/sideload_schemas/comment_count.json
tap_zendesk/schemas/sideload_schemas/dates.json
tap_zendesk/schemas/sideload_schemas/metric_sets.json
tap_zendesk/schemas/sideload_schemas/slas.json
twilio_tap_zendesk-1.0.14.dist-info/LICENSE
twilio_tap_zendesk-1.0.14.dist-info/METADATA
twilio_tap_zendesk-1.0.14.dist-info/WHEEL
twilio_tap_zendesk-1.0.14.dist-info/entry_points.txt
twilio_tap_zendesk-1.0.14.dist-info/top_level.txt
twilio_tap_zendesk-1.0.14.dist-info/RECORD
